cksechcalc/__init__.py
cksechcalc/add.py
cksechcalc/divide.py
cksechcalc/multiply.py
cksechcalc/subtract.py
cksechcalc/ver.py
cksechcalc1310d5125-0.4.0.dist-info/METADATA
cksechcalc1310d5125-0.4.0.dist-info/WHEEL
cksechcalc1310d5125-0.4.0.dist-info/top_level.txt
cksechcalc1310d5125-0.4.0.dist-info/RECORD
